mecore/__init__.py
mecore-0.0.1.dist-info/METADATA
mecore-0.0.1.dist-info/WHEEL
mecore-0.0.1.dist-info/top_level.txt
mecore-0.0.1.dist-info/RECORD
