Metadata-Version: 2.4
Name: mecore
Version: 0.0.1
Summary: Implementation coming soon.
Author: Kinson Vernet
License-Expression: MIT
Classifier: Development Status :: 1 - Planning
Classifier: Programming Language :: Python :: 3
Requires-Python: >=3.10
